LICENSE
MANIFEST.in
README.md
setup.cfg
setup.py
usb_ser_mon/__init__.py
usb_ser_mon/find_port.py
usb_ser_mon/mk-udev-rules-pyboard.sh
usb_ser_mon/mk-udev-rules-stm32.sh
usb_ser_mon/mk-udev-rules-teensy.sh
usb_ser_mon/usb_ser_mon.py
usb_ser_mon.egg-info/PKG-INFO
usb_ser_mon.egg-info/SOURCES.txt
usb_ser_mon.egg-info/dependency_links.txt
usb_ser_mon.egg-info/entry_points.txt
usb_ser_mon.egg-info/requires.txt
usb_ser_mon.egg-info/top_level.txt