Metadata-Version: 2.1
Name: usb-ser-mon
Version: 0.0.1
Summary: A serial monitor for USB Serial devices
Home-page: https://github.com/dhylands/usb-ser-mon/
Author: Dave Hylands
Author-email: dhylands@gmail.com
License: UNKNOWN
Keywords: usb serial
Platform: UNKNOWN
Classifier: Development Status :: 3 - Alpha
Classifier: Intended Audience :: Developers
Classifier: Topic :: Software Development :: Build Tools
Classifier: License :: OSI Approved :: MIT License
Classifier: Intended Audience :: Science/Research
Classifier: License :: OSI Approved :: BSD License
Classifier: Operating System :: MacOS :: MacOS X
Classifier: Operating System :: POSIX
Classifier: Programming Language :: Python
Classifier: Programming Language :: Python :: 3.2
Classifier: Programming Language :: Python :: 3.3
Classifier: Programming Language :: Python :: 3.4
Classifier: Topic :: Scientific/Engineering
Classifier: Topic :: Software Development :: Libraries
